{ "fe-activity": 59905, "fe-airplay": 59906, "fe-alert-circle": 59907, "fe-alert-octagon": 59909, "fe-alert-triangle": 59908, "fe-align-center": 59910, "fe-align-justify": 59911, "fe-align-left": 59912, "fe-align-right": 59913, "fe-anchor": 59914, "fe-aperture": 59915, "fe-archive": 59916, "fe-arrow-down-circle": 59917, "fe-arrow-down-left": 59918, "fe-arrow-down-right": 59919, "fe-arrow-down": 59920, "fe-arrow-left-circle": 59921, "fe-arrow-left": 59922, "fe-arrow-right-circle": 59923, "fe-arrow-right": 59924, "fe-arrow-up-circle": 59925, "fe-arrow-up-left": 59926, "fe-arrow-up-right": 59927, "fe-arrow-up": 59928, "fe-at-sign": 59929, "fe-award": 59930, "fe-bar-chart-2": 59931, "fe-bar-chart": 59932, "fe-battery-charging": 59933, "fe-battery": 59934, "fe-bell-off": 59935, "fe-bell": 59936, "fe-bluetooth": 59937, "fe-bold": 59938, "fe-book-open": 59939, "fe-book": 59940, "fe-bookmark": 59941, "fe-box": 59942, "fe-briefcase": 59943, "fe-calendar": 59944, "fe-camera-off": 59945, "fe-camera": 59946, "fe-cast": 59947, "fe-check-circle": 59948, "fe-check-square": 59949, "fe-check": 59950, "fe-chevron-down": 59951, "fe-chevron-left": 59952, "fe-chevron-right": 59953, "fe-chevron-up": 59954, "fe-chevrons-down": 59955, "fe-chevrons-left": 59956, "fe-chevrons-right": 59957, "fe-chevrons-up": 59958, "fe-chrome": 59959, "fe-circle": 59960, "fe-clipboard": 59961, "fe-clock": 59962, "fe-cloud-drizzle": 59963, "fe-cloud-lightning": 59964, "fe-cloud-off": 59965, "fe-cloud-rain": 59966, "fe-cloud-snow": 59967, "fe-cloud": 59968, "fe-code": 59969, "fe-codepen": 59970, "fe-codesandbox": 59971, "fe-coffee": 59972, "fe-columns": 59973, "fe-command": 59974, "fe-compass": 59975, "fe-copy": 59976, "fe-corner-down-left": 59977, "fe-corner-down-right": 59978, "fe-corner-left-down": 59979, "fe-corner-left-up": 59980, "fe-corner-right-down": 59981, "fe-corner-right-up": 59982, "fe-corner-up-left": 59983, "fe-corner-up-right": 59984, "fe-cpu": 59985, "fe-credit-card": 59986, "fe-crop": 59987, "fe-crosshair": 59988, "fe-database": 59989, "fe-delete": 59990, "fe-disc": 59991, "fe-dollar-sign": 59992, "fe-download-cloud": 59993, "fe-download": 59994, "fe-droplet": 59995, "fe-edit-2": 59996, "fe-edit-3": 59997, "fe-edit": 59998, "fe-external-link": 59999, "fe-eye-off": 60000, "fe-eye": 60001, "fe-facebook": 60002, "fe-fast-forward": 60003, "fe-feather": 60004, "fe-figma": 60005, "fe-file-minus": 60006, "fe-file-plus": 60007, "fe-file-text": 60008, "fe-file": 60009, "fe-film": 60010, "fe-filter": 60011, "fe-flag": 60012, "fe-folder-minus": 60013, "fe-folder-plus": 60014, "fe-folder": 60015, "fe-frown": 60016, "fe-gift": 60017, "fe-git-branch": 60018, "fe-git-commit": 60019, "fe-git-merge": 60020, "fe-git-pull-request": 60021, "fe-github": 60022, "fe-gitlab": 60023, "fe-globe": 60024, "fe-grid": 60025, "fe-hard-drive": 60026, "fe-hash": 60027, "fe-headphones": 60028, "fe-heart": 60029, "fe-help-circle": 60030, "fe-hexagon": 60031, "fe-home": 60032, "fe-image": 60033, "fe-inbox": 60034, "fe-info": 60035, "fe-instagram": 60036, "fe-italic": 60037, "fe-key": 60038, "fe-layers": 60039, "fe-layout": 60040, "fe-life-buoy": 60041, "fe-link-2": 60042, "fe-link": 60043, "fe-linkedin": 60044, "fe-list": 60045, "fe-loader": 60047, "fe-lock": 60046, "fe-log-in": 60048, "fe-log-out": 60049, "fe-mail": 60050, "fe-map-pin": 60051, "fe-map": 60052, "fe-maximize-2": 60053, "fe-maximize": 60054, "fe-meh": 60055, "fe-menu": 60056, "fe-message-circle": 60057, "fe-message-square": 60058, "fe-mic-off": 60059, "fe-mic": 60060, "fe-minimize-2": 60061, "fe-minimize": 60062, "fe-minus-circle": 60063, "fe-minus-square": 60064, "fe-minus": 60065, "fe-monitor": 60066, "fe-moon": 60067, "fe-more-horizontal": 60068, "fe-more-vertical": 60069, "fe-mouse-pointer": 60070, "fe-move": 60071, "fe-music": 60072, "fe-navigation-2": 60073, "fe-navigation": 60074, "fe-octagon": 60075, "fe-package": 60076, "fe-paperclip": 60077, "fe-pause-circle": 60078, "fe-pause": 60079, "fe-pen-tool": 60080, "fe-percent": 60081, "fe-phone-call": 60082, "fe-phone-forwarded": 60083, "fe-phone-incoming": 60084, "fe-phone-missed": 60085, "fe-phone-off": 60086, "fe-phone-outgoing": 60087, "fe-phone": 60088, "fe-pie-chart": 60089, "fe-play-circle": 60090, "fe-play": 60091, "fe-plus-circle": 60092, "fe-plus-square": 60093, "fe-plus": 60094, "fe-pocket": 60095, "fe-power": 60096, "fe-printer": 60097, "fe-radio": 60098, "fe-refresh-ccw": 60099, "fe-refresh-cw": 60100, "fe-repeat": 60101, "fe-rewind": 60102, "fe-rotate-ccw": 60103, "fe-rotate-cw": 60104, "fe-rss": 60105, "fe-save": 60106, "fe-scissors": 60107, "fe-search": 60108, "fe-send": 60109, "fe-server": 60110, "fe-settings": 60111, "fe-share-2": 60112, "fe-share": 60113, "fe-shield-off": 60114, "fe-shield": 60115, "fe-shopping-bag": 60116, "fe-shopping-cart": 60117, "fe-shuffle": 60118, "fe-sidebar": 60119, "fe-skip-back": 60120, "fe-skip-forward": 60121, "fe-slack": 60122, "fe-slash": 60123, "fe-sliders": 60124, "fe-smartphone": 60125, "fe-smile": 60126, "fe-speaker": 60127, "fe-square": 60128, "fe-star": 60129, "fe-stop-circle": 60130, "fe-sun": 60131, "fe-sunrise": 60132, "fe-sunset": 60133, "fe-tablet": 60134, "fe-tag": 60135, "fe-target": 60136, "fe-terminal": 60137, "fe-thermometer": 60138, "fe-thumbs-down": 60139, "fe-thumbs-up": 60140, "fe-toggle-left": 60141, "fe-toggle-right": 60142, "fe-trash-2": 60143, "fe-trash": 60144, "fe-trello": 60145, "fe-trending-down": 60146, "fe-trending-up": 60147, "fe-triangle": 60148, "fe-truck": 60149, "fe-tv": 60150, "fe-twitter": 60151, "fe-type": 60152, "fe-umbrella": 60153, "fe-underline": 60154, "fe-unlock": 60155, "fe-upload-cloud": 60156, "fe-upload": 60157, "fe-user-check": 60158, "fe-user-minus": 60159, "fe-user-plus": 60160, "fe-user-x": 60161, "fe-user": 60162, "fe-users": 60163, "fe-video-off": 60164, "fe-video": 60165, "fe-voicemail": 60166, "fe-volume-1": 60167, "fe-volume-2": 60168, "fe-volume-x": 60169, "fe-volume": 60170, "fe-watch": 60171, "fe-wifi-off": 60172, "fe-wifi": 60173, "fe-wind": 60174, "fe-x-circle": 60175, "fe-x-octagon": 60176, "fe-x-square": 60177, "fe-x": 60178, "fe-youtube": 60179, "fe-zap-off": 60180, "fe-zap": 60181, "fe-zoom-in": 60182, "fe-zoom-out": 60183}